domino/__init__.py
domino/_custom_metrics.py
domino/_version.py
domino/authentication.py
domino/constants.py
domino/data_sources.py
domino/datasets.py
domino/domino.py
domino/domino_enums.py
domino/exceptions.py
domino/helpers.py
domino/http_request_manager.py
domino/routes.py
domino/training_sets.py
domino/_impl/__init__.py
domino/_impl/custommetrics/__init__.py
domino/_impl/custommetrics/api_client.py
domino/_impl/custommetrics/configuration.py
domino/_impl/custommetrics/exceptions.py
domino/_impl/custommetrics/rest.py
domino/_impl/custommetrics/schemas.py
domino/_impl/custommetrics/apis/__init__.py
domino/_impl/custommetrics/apis/path_to_api.py
domino/_impl/custommetrics/apis/tag_to_api.py
domino/_impl/custommetrics/apis/paths/__init__.py
domino/_impl/custommetrics/apis/paths/api_metric_alerts_v1.py
domino/_impl/custommetrics/apis/paths/api_metric_values_v1.py
domino/_impl/custommetrics/apis/paths/api_metric_values_v1_model_monitoring_id_metric.py
domino/_impl/custommetrics/apis/tags/__init__.py
domino/_impl/custommetrics/apis/tags/custom_metrics_api.py
domino/_impl/custommetrics/model/__init__.py
domino/_impl/custommetrics/model/failure_envelope_v1.py
domino/_impl/custommetrics/model/failure_envelope_v1.pyi
domino/_impl/custommetrics/model/invalid_body_envelope_v1.py
domino/_impl/custommetrics/model/invalid_body_envelope_v1.pyi
domino/_impl/custommetrics/model/metadata_v1.py
domino/_impl/custommetrics/model/metadata_v1.pyi
domino/_impl/custommetrics/model/metric_alert_request_v1.py
domino/_impl/custommetrics/model/metric_alert_request_v1.pyi
domino/_impl/custommetrics/model/metric_tag_v1.py
domino/_impl/custommetrics/model/metric_tag_v1.pyi
domino/_impl/custommetrics/model/metric_value_v1.py
domino/_impl/custommetrics/model/metric_value_v1.pyi
domino/_impl/custommetrics/model/metric_values_envelope_v1.py
domino/_impl/custommetrics/model/metric_values_envelope_v1.pyi
domino/_impl/custommetrics/model/new_metric_value_v1.py
dominodatalab-1.5.1.dist-info/licenses/LICENSE.txt
dominodatalab-1.5.1.dist-info/METADATA
dominodatalab-1.5.1.dist-info/WHEEL
dominodatalab-1.5.1.dist-info/top_level.txt
dominodatalab-1.5.1.dist-info/RECORD
