Metadata-Version: 2.4
Name: dominodatalab
Version: 1.5.1
Summary: Python bindings for the Domino API
Home-page: https://github.com/dominodatalab/python-domino
Download-URL: https://github.com/dominodatalab/python-domino/archive/Release-1.5.1.zip
Author: Domino Data Lab
Author-email: support@dominodatalab.com
License: Apache Software License (Apache 2.0)
Keywords: Domino Data Lab,API
Requires-Python: >=3.10.0
License-File: LICENSE.txt
Requires-Dist: packaging==23.2
Requires-Dist: requests>=2.4.2
Requires-Dist: beautifulsoup4~=4.11
Requires-Dist: polling2~=0.5.0
Requires-Dist: urllib3<3,>=1.26.19
Requires-Dist: typing-extensions~=4.13.0
Requires-Dist: frozendict~=2.3
Requires-Dist: python-dateutil~=2.8.2
Requires-Dist: retry==0.9.2
Provides-Extra: airflow
Requires-Dist: apache-airflow==2.2.4; extra == "airflow"
Provides-Extra: data
Requires-Dist: dominodatalab-data>=0.1.0; extra == "data"
Provides-Extra: aisystems
Requires-Dist: semver>=3.0.4; extra == "aisystems"
Requires-Dist: pandas>=2.3.1; extra == "aisystems"
Requires-Dist: numpy>=2.0.2; extra == "aisystems"
Requires-Dist: mlflow-skinny==3.2.0; extra == "aisystems"
Requires-Dist: mlflow-tracing==3.2.0; extra == "aisystems"
Provides-Extra: dev
Requires-Dist: pytest-order>=1.3.0; extra == "dev"
Requires-Dist: pytest-asyncio>=0.23.8; extra == "dev"
Requires-Dist: scikit-learn>=1.6.1; extra == "dev"
Requires-Dist: black==22.3.0; extra == "dev"
Requires-Dist: flake8==4.0.1; extra == "dev"
Requires-Dist: Jinja2==2.11.3; extra == "dev"
Requires-Dist: nbconvert==6.3.0; extra == "dev"
Requires-Dist: packaging==23.2; extra == "dev"
Requires-Dist: polling2==0.5.0; extra == "dev"
Requires-Dist: pre-commit==2.19.0; extra == "dev"
Requires-Dist: pyspark==3.3.0; extra == "dev"
Requires-Dist: pytest==7.4.3; extra == "dev"
Requires-Dist: requests_mock==1.9.3; extra == "dev"
Requires-Dist: tox==3.25.1; extra == "dev"
Requires-Dist: frozendict==2.4.6; extra == "dev"
Requires-Dist: docker>=7.1.0; extra == "dev"
Requires-Dist: pytest-mock>=3.14.1; extra == "dev"
Dynamic: author
Dynamic: author-email
Dynamic: description
Dynamic: description-content-type
Dynamic: download-url
Dynamic: home-page
Dynamic: keywords
Dynamic: license
Dynamic: license-file
Dynamic: provides-extra
Dynamic: requires-dist
Dynamic: requires-python
Dynamic: summary
